Orange3_Sqlite3-0.0.4-py3.11-nspkg.pth
orangecontrib/sqlite3/__init__.py
orangecontrib/sqlite3/widgets/__init__.py
orangecontrib/sqlite3/widgets/owsqlite3.py
orangecontrib/sqlite3/widgets/icons/sqlite3.svg
Orange3_Sqlite3-0.0.4.dist-info/METADATA
Orange3_Sqlite3-0.0.4.dist-info/WHEEL
Orange3_Sqlite3-0.0.4.dist-info/entry_points.txt
Orange3_Sqlite3-0.0.4.dist-info/namespace_packages.txt
Orange3_Sqlite3-0.0.4.dist-info/top_level.txt
Orange3_Sqlite3-0.0.4.dist-info/RECORD
